pysnic/__init__.py
pysnic/algorithms/__init__.py
pysnic/algorithms/polygonize.py
pysnic/algorithms/ramerDouglasPeucker.py
pysnic/algorithms/snic.py
pysnic/examples/__init__.py
pysnic/examples/minimal.py
pysnic/examples/polygons.py
pysnic/examples/postProcess.py
pysnic/examples/superPixels.py
pysnic/examples/timing.py
pysnic/helpers/__init__.py
pysnic/helpers/grid.py
pysnic/metric/__init__.py
pysnic/metric/snic.py
pysnic/ndim/__init__.py
pysnic/ndim/lerp.py
pysnic/ndim/norm_sqr.py
pysnic/ndim/operations.py
pysnic/ndim/operations_collections.py
pysnic-1.0.4.dist-info/LICENSE.md
pysnic-1.0.4.dist-info/METADATA
pysnic-1.0.4.dist-info/WHEEL
pysnic-1.0.4.dist-info/top_level.txt
pysnic-1.0.4.dist-info/RECORD
