Metadata-Version: 2.1
Name: pysnic
Version: 1.0.4
Summary: SNIC superpixels algorithm
Home-page: https://github.com/MoritzWillig/pysnic
Author: Moritz Willig
Author-email: moritz@rise-of-light.de
License: MIT
Keywords: image processing,computer vision,image segmentation,superpixels,SNIC
Platform: UNKNOWN
Classifier: Programming Language :: Python :: 3.5
Classifier: License :: OSI Approved :: MIT License
Classifier: Operating System :: OS Independent
Classifier: Topic :: Scientific/Engineering :: Image Recognition
Requires-Python: >=3.5
Provides-Extra: examples
Requires-Dist: scikit-image ; extra == 'examples'
Requires-Dist: numpy ; extra == 'examples'
Requires-Dist: matplotlib ; extra == 'examples'
Requires-Dist: pillow ; extra == 'examples'
